pyonstar/__init__.py
pyonstar/api.py
pyonstar/auth.py
pyonstar/client.py
pyonstar/commands.py
pyonstar/types.py
pyonstar/auth/__init__.py
pyonstar/auth/api.py
pyonstar/auth/constants.py
pyonstar/auth/gm_auth.py
pyonstar/auth/types.py
pyonstar/auth/utils.py
tests/__init__.py
tests/conftest.py
tests/pyonstar/__init__.py
tests/pyonstar/test_api.py
tests/pyonstar/test_auth.py
tests/pyonstar/test_client.py
tests/pyonstar/test_commands.py
tests/pyonstar/test_onstar_api_client.py
tests/pyonstar/test_utils.py
pyonstar-0.0.14.dist-info/METADATA
pyonstar-0.0.14.dist-info/WHEEL
pyonstar-0.0.14.dist-info/top_level.txt
pyonstar-0.0.14.dist-info/RECORD
