Metadata-Version: 2.4
Name: pyonstar
Version: 0.0.14
Summary: Unofficial package for making OnStar API requests
Author: Bryan Leboff
Author-email: Bryan Leboff <leboff@gmail.com>
License: MIT License
Project-URL: Homepage, https://github.com/leboff/pyonstar
Project-URL: Bug Tracker, https://github.com/leboff/pyonstar/issues
Classifier: Development Status :: 4 - Beta
Classifier: Intended Audience :: Developers
Classifier: License :: OSI Approved :: MIT License
Classifier: Programming Language :: Python :: 3
Classifier: Programming Language :: Python :: 3.10
Classifier: Programming Language :: Python :: 3.11
Requires-Python: >=3.10
Requires-Dist: httpx>=0.24.0
Requires-Dist: pyjwt>=2.8.0
Requires-Dist: pyotp>=2.9.0
Requires-Dist: aiofiles>=23.2.1
Dynamic: author
Dynamic: requires-python
